tet/__init__.py
tet/request.py
tet/response.py
tet/session.py
tet/config/__init__.py
tet/decorators/__init__.py
tet/i18n/__init__.py
tet/interface/__init__.py
tet/renderers/__init__.py
tet/renderers/json.py
tet/renderers/tonnikala.py
tet/security/__init__.py
tet/security/authorization.py
tet/security/csrf.py
tet/sqlalchemy/__init__.py
tet/sqlalchemy/factory.py
tet/sqlalchemy/password.py
tet/sqlalchemy/simple.py
tet/static/__init__.py
tet/util/__init__.py
tet/util/base64.py
tet/util/collections.py
tet/util/crypt.py
tet/util/export.py
tet/util/json.py
tet/util/path.py
tet/util/pshell.py
tet/view/__init__.py
tet/viewlet/__init__.py
tet-0.4.1.dist-info/LICENSE
tet-0.4.1.dist-info/METADATA
tet-0.4.1.dist-info/WHEEL
tet-0.4.1.dist-info/top_level.txt
tet-0.4.1.dist-info/RECORD
