Metadata-Version: 2.1
Name: tet
Version: 0.4.1
Summary: Unearthly intelligent batteries-included application framework built on Pyramid
Home-page: http://www.anttipatterns.com
Author: Antti Haapala
Author-email: antti.haapala@anttipatterns.com
Keywords: web wsgi bfg pylons pyramid
Classifier: Development Status :: 4 - Beta
Classifier: Framework :: Pyramid
Classifier: Intended Audience :: Developers
Classifier: License :: OSI Approved :: Python Software Foundation License
Classifier: Programming Language :: Python :: 3.6
Classifier: Programming Language :: Python :: 3.7
Classifier: Programming Language :: Python :: 3.8
Classifier: Programming Language :: Python :: 3.9
Classifier: Programming Language :: Python :: 3.10
Classifier: Programming Language :: Python :: 3.11
Classifier: Programming Language :: Python :: 3 :: Only
Classifier: Topic :: Internet :: WWW/HTTP :: WSGI
Classifier: Topic :: Internet :: WWW/HTTP :: WSGI :: Application
Classifier: Topic :: Internet :: WWW/HTTP :: WSGI :: Middleware
Classifier: Topic :: Software Development :: Libraries :: Application Frameworks
License-File: LICENSE
Requires-Dist: pyramid >=1.9
Requires-Dist: passlib
Requires-Dist: sqlalchemy
Requires-Dist: pyramid-di
Provides-Extra: dev
Requires-Dist: pytest ; extra == 'dev'
